P4J/__init__.py
P4J/base_periodogram.py
P4J/generator.py
P4J/math.py
P4J/periodograms.py
P4J/algorithms/__init__.py
P4J/algorithms/analysis_of_variance.c
P4J/algorithms/analysis_of_variance.cpython-38-x86_64-linux-gnu.so
P4J/algorithms/analysis_of_variance.pyx
P4J/algorithms/multiharmonic_aov.c
P4J/algorithms/multiharmonic_aov.cpython-38-x86_64-linux-gnu.so
P4J/algorithms/multiharmonic_aov.pyx
P4J/algorithms/mutual_information.c
P4J/algorithms/mutual_information.cpython-38-x86_64-linux-gnu.so
P4J/algorithms/mutual_information.pyx
P4J/algorithms/phase_dispersion_minimization.c
P4J/algorithms/phase_dispersion_minimization.cpython-38-x86_64-linux-gnu.so
P4J/algorithms/phase_dispersion_minimization.pyx
P4J/algorithms/string_length.c
P4J/algorithms/string_length.cpython-38-x86_64-linux-gnu.so
P4J/algorithms/string_length.pyx
P4J/algorithms/utilities.c
P4J/algorithms/utilities.cpython-38-x86_64-linux-gnu.so
P4J/algorithms/utilities.pxd
P4J/algorithms/utilities.pyx
P4J-1.1.2.dist-info/LICENSE
P4J-1.1.2.dist-info/METADATA
P4J-1.1.2.dist-info/WHEEL
P4J-1.1.2.dist-info/top_level.txt
P4J-1.1.2.dist-info/RECORD
