Metadata-Version: 2.1
Name: P4J
Version: 1.1.2
Summary: Periodic light curve analysis tools based on Information Theory
Author-email: Pablo Huijse <pablo.huijse@gmail.com>
Project-URL: Homepage, https://github.com/phuijse/P4J
Project-URL: Repository, https://github.com/phuijse/P4J
Keywords: astronomy,time series,period estimation,information theory
Classifier: Natural Language :: English
Classifier: Development Status :: 4 - Beta
Classifier: Intended Audience :: Science/Research
Classifier: Topic :: Scientific/Engineering :: Astronomy
Classifier: Programming Language :: Python
Classifier: Programming Language :: Cython
Requires-Python: >=3.8
License-File: LICENSE
Requires-Dist: numpy >1.19.0
Requires-Dist: scipy
